{"id":1041,"name":"応用認知科学 / APPLIED COGNITIVE SCIENCE","account_id":1,"uuid":"7QgLCz2EFj2aBEPVx17DidtR6nWm6KK8K9Idbkoe","start_at":null,"grading_standard_id":null,"is_public":false,"created_at":"2020-10-01T04:40:25Z","syllabus_body":"\u003ctable style=\"width: 100%; margin: 0; border-collapse: collapse; background-color: #394B58; color: white;\" border=\"1\"\u003e\n  \u003ctbody\u003e\n      \u003ctr\u003e\n        \u003ctd style=\"width: 50%;\"\u003e\n          C2032\u003cbr\u003e\n          応用認知科学\u003cbr\u003e\n          \u003cspan style=\"color: #c9c9c9;\"\u003eAPPLIED COGNITIVE SCIENCE\u003c/span\u003e\n        \u003c/td\u003e\n        \u003ctd\u003e\n          特設科目\u003cbr\u003e\n          \u003cspan style=\"color: #c9c9c9;\"\u003eSpecial Seminars\u003c/span\u003e\u003cbr\u003e\n          2 単位\n        \u003c/td\u003e\n      \u003c/tr\u003e\n  \u003c/tbody\u003e\n\u003c/table\u003e\n\n\u003ctable style=\"width: 100%; margin: 0; border-collapse: collapse; border: 1px solid #C7CDD1;\" border=\"1\"\u003e\n  \u003ctbody\u003e\n    \u003ctr\u003e\n      \u003ctd style=\"width: 25%; background-color: #F5F5F5; border-color: #C7CDD1;\"\u003e実施形態\u003c/td\u003e\n      \u003ctd style=\"border-color: #C7CDD1;\"\u003eオンキャンパス\u003c/td\u003e\n    \u003c/tr\u003e\n    \u003ctr\u003e\n      \u003ctd style=\"background-color: #F5F5F5; border-color: #C7CDD1;\"\u003e開催日程\u003c/td\u003e\n      \u003ctd style=\"border-color: #C7CDD1;\"\u003e秋学期 金曜日４時限,金曜日５時限\u003c/td\u003e\n    \u003c/tr\u003e\n    \u003ctr\u003e\n      \u003ctd style=\"background-color: #F5F5F5; border-color: #C7CDD1;\"\u003e担当教員\u003c/td\u003e\n      \u003ctd style=\"border-color: #C7CDD1;\"\u003e小俣 貴宣（オマタ タカノブ）\u003c/td\u003e\n    \u003c/tr\u003e\n    \u003ctr\u003e\n      \u003ctd style=\"background-color: #F5F5F5; border-color: #C7CDD1;\"\u003e関連科目\u003c/td\u003e\n      \u003ctd style=\"border-color: #C7CDD1;\"\u003e\n          前提科目（推奨）: C2031\u003cbr\u003e\n          前提科目（関連）: C2094,60390,C2115,C2055,C2108,C2116,X1022,X1033,65250,X1041,60460\u003cbr\u003e\n      \u003c/td\u003e\n    \u003c/tr\u003e\n    \u003ctr\u003e\n      \u003ctd style=\"background-color: #F5F5F5; border-color: #C7CDD1;\"\u003e開講場所\u003c/td\u003e\n      \u003ctd style=\"border-color: #C7CDD1;\"\u003eSFC・TBD（フィールドワークを実施する場合がある）\u003c/td\u003e\n    \u003c/tr\u003e\n    \u003ctr\u003e\n      \u003ctd style=\"background-color: #F5F5F5; border-color: #C7CDD1;\"\u003e授業形態\u003c/td\u003e\n      \u003ctd style=\"border-color: #C7CDD1;\"\u003e講義、実習・演習、グループワーク、遠隔あり\u003c/td\u003e\n    \u003c/tr\u003e\n    \u003ctr\u003e\n      \u003ctd style=\"background-color: #F5F5F5; border-color: #C7CDD1;\"\u003e履修者制限\u003c/td\u003e\n      \u003ctd style=\"border-color: #C7CDD1;\"\u003e\n          \u003cp\u003e履修人数を制限する\u003cbr\u003e\u003cbr\u003e受入学生数（予定）：約 30 人\u003cbr\u003e選抜方法：課題提出による選抜\u003cbr\u003e\u003cbr\u003e【課題内容】\u003cbr\u003e課題１：これまでの心理学の学習経験について教えてください（例：「発達心理学の本を数冊読んだことがある」「小規模な心理学実験を行ったことがある」など箇条書きで構いません）。\u003cbr\u003e\u003cbr\u003e課題２：この授業の履修を希望する理由を教えてください（400字程度）。\u003cbr\u003e\u003cbr\u003e課題３：大学で学んだ学術的な知識が産業・社会でどのように役立つと思うか、あなたご自身の考えを教えてください（400字程度）。\u003cbr\u003e\u003cbr\u003e\u003cbr\u003e\u003cbr\u003e◯エントリー〆切日時：2020年9月28日（月） 17:00\u003cbr\u003e◯履修許可者発表日時：2020年9月30日（水） 17:00\u003cbr\u003e\u003cbr\u003e◯テキスト入力\u003cbr\u003e\u003c/p\u003e\n          \u003cp style=\"color: #856a5d;\"\u003eOnly the selected students can take this course.\u003cbr\u003e\u003cbr\u003eNumber of students in the class (scheduled) : About 30\u003cbr\u003ePre-registration screening by submitted an assignment\u003cbr\u003e\u003cbr\u003e【ASSIGNMENT】\u003cbr\u003e課題１：これまでの心理学の学習経験について教えてください（例：「発達心理学の本を数冊読んだことがある」「小規模な心理学実験を行ったことがある」など箇条書きで構いません）。\u003cbr\u003e\u003cbr\u003e課題２：この授業の履修を希望する理由を教えてください（400字程度）。\u003cbr\u003e\u003cbr\u003e課題３：大学で学んだ学術的な知識が産業・社会でどのように役立つと思うか、あなたご自身の考えを教えてください（400字程度）。\u003cbr\u003e\u003cbr\u003e\u003cbr\u003e\u003cbr\u003e* Schedule: TBD\u003c/p\u003e\n      \u003c/td\u003e\n    \u003c/tr\u003e\n    \u003ctr\u003e\n      \u003ctd style=\"background-color: #F5F5F5; border-color: #C7CDD1;\"\u003e履修条件\u003c/td\u003e\n      \u003ctd style=\"border-color: #C7CDD1;\"\u003e\n        \u003cp\u003e\u003c/p\u003e\n        \u003cp style=\"color: #856a5d;\"\u003e\u003c/p\u003e\n        \u003cp\u003e(1) 認知心理学、人間工学の基礎を学んでおくこと\u003cbr\u003e\u003cbr\u003e(2) 授業中、議論や発表が求められることから、そのため知識水準やコミュニケーション力があること\u003cbr\u003e\u003c/p\u003e\n        \u003cp style=\"color: #856a5d;\"\u003e(1) Fundamental knowledge of cognitive psychology and ergonomics/human factor\u003cbr\u003e(2) Good communication skills to make discussions and presentations in the class interactive\u003cbr\u003e\u003c/p\u003e\n      \u003c/td\u003e\n    \u003c/tr\u003e\n    \u003ctr\u003e\n      \u003ctd style=\"background-color: #F5F5F5; border-color: #C7CDD1;\"\u003e使用言語\u003c/td\u003e\n      \u003ctd style=\"border-color: #C7CDD1;\"\u003e日本語\u003c/td\u003e\n    \u003c/tr\u003e\n    \u003ctr\u003e\n      \u003ctd style=\"background-color: #F5F5F5; border-color: #C7CDD1;\"\u003e連絡先\u003c/td\u003e\n      \u003ctd style=\"border-color: #C7CDD1;\"\u003etomata@sfc.keio.ac.jp\u003c/td\u003e\n    \u003c/tr\u003e\n    \u003ctr\u003e\n      \u003ctd style=\"background-color: #F5F5F5; border-color: #C7CDD1;\"\u003e授業ホームページ\u003c/td\u003e\n      \u003ctd style=\"border-color: #C7CDD1;\"\u003e\u003c/td\u003e\n    \u003c/tr\u003e\n    \u003ctr\u003e\n      \u003ctd style=\"background-color: #F5F5F5; border-color: #C7CDD1;\"\u003e同一科目\u003c/td\u003e\n      \u003ctd style=\"border-color: #C7CDD1;\"\u003e\n        \u003cp\u003e\u003c/p\u003e\n        \u003cp style=\"color: #856a5d;\"\u003e\u003c/p\u003e\n      \u003c/td\u003e\n    \u003c/tr\u003e\n    \u003ctr\u003e\n      \u003ctd style=\"background-color: #F5F5F5; border-color: #C7CDD1;\"\u003e学生が利用する予定機材/ソフト等\u003c/td\u003e\n      \u003ctd style=\"border-color: #C7CDD1;\"\u003e\n        \u003cp\u003e\u003c/p\u003e\n        \u003cp style=\"color: #856a5d;\"\u003e\u003c/p\u003e\n      \u003c/td\u003e\n    \u003c/tr\u003e\n    \u003ctr\u003e\n      \u003ctd style=\"background-color: #F5F5F5; border-color: #C7CDD1;\"\u003e設置学部・研究科\u003c/td\u003e\n      \u003ctd style=\"border-color: #C7CDD1;\"\u003e総合政策・環境情報学部\u003c/td\u003e\n    \u003c/tr\u003e\n    \u003ctr\u003e\n      \u003ctd style=\"background-color: #F5F5F5; border-color: #C7CDD1;\"\u003e大学院プロジェクト名\u003c/td\u003e\n      \u003ctd style=\"border-color: #C7CDD1;\"\u003e\u003cp style=\"color: #856a5d;\"\u003e\u003c/p\u003e\u003c/td\u003e\n    \u003c/tr\u003e\n    \u003ctr\u003e\n      \u003ctd style=\"background-color: #F5F5F5; border-color: #C7CDD1;\"\u003e大学院プロジェクトサブメンバー\u003c/td\u003e\n      \u003ctd style=\"border-color: #C7CDD1;\"\u003e\n        \u003cp\u003e\u003c/p\u003e\n        \u003cp style=\"color: #856a5d;\"\u003e\u003c/p\u003e\n      \u003c/td\u003e\n    \u003c/tr\u003e\n    \u003ctr\u003e\n      \u003ctd style=\"background-color: #F5F5F5; border-color: #C7CDD1;\"\u003eゲストスピーカーの人数\u003c/td\u003e\n      \u003ctd style=\"border-color: #C7CDD1;\"\u003e0\u003c/td\u003e\n    \u003c/tr\u003e\n    \u003ctr\u003e\n      \u003ctd style=\"background-color: #F5F5F5; border-color: #C7CDD1;\"\u003e履修選抜・課題タイプ=テキスト登録可\u003c/td\u003e\n      \u003ctd style=\"border-color: #C7CDD1;\"\u003etrue\u003c/td\u003e\n    \u003c/tr\u003e\n    \u003ctr\u003e\n      \u003ctd style=\"background-color: #F5F5F5; border-color: #C7CDD1;\"\u003e履修選抜・選抜課題タイプ=ファイル登録可\u003c/td\u003e\n      \u003ctd style=\"border-color: #C7CDD1;\"\u003efalse\u003c/td\u003e\n    \u003c/tr\u003e\n    \u003ctr\u003e\n      \u003ctd style=\"background-color: #F5F5F5; border-color: #C7CDD1;\"\u003eGIGAサティフィケート対象\u003c/td\u003e\n      \u003ctd style=\"border-color: #C7CDD1;\"\u003e\u003c/td\u003e\n    \u003c/tr\u003e\n    \u003ctr\u003e\n      \u003ctd style=\"background-color: #F5F5F5; border-color: #C7CDD1;\"\u003e最終更新日\u003c/td\u003e\n      \u003ctd style=\"border-color: #C7CDD1;\"\u003e2020/08/26 08:52:32\u003c/td\u003e\n    \u003c/tr\u003e\n  \u003c/tbody\u003e\n\u003c/table\u003e\n\n\n\n\n\u003ch3 style=\"background-color: #394B58; color: white; padding-left: 8px; font-weight: bold;\"\u003e科目概要\u003c/h3\u003e\n\n\u003cp\u003e認知科学やその関連領域を学ぶことの効用は、人間の心理や行動の科学的な理解にとどまらず、社会や産業の様々な問題に対する効果的な解決方法の創出にも役立ちます。この授業では、皆さんが将来直面するであろう実世界の問題の解決において、そうした知識を効果的かつ創造的に応用するために必要な素養の習得を目指します。\u003cbr\u003e\u003cbr\u003e今年度は、数ある認知科学の関連研究の中からアフォーダンスとシグニファイア、視知覚、意思決定と認知バイアス、モチベーションと行動変容の４つのトピックを取り上げます。毎週、その理論的な基礎について解説し、その後、特にデザインの分野やマーケティングの分野における実践的な応用の有用性や課題についてケーススタディを交えつつ共に考察していきたいと思います。\u003cbr\u003e特に学術的知識の実践的応用に強い関心と意欲のある方の参加を歓迎します。\u003cbr\u003e\u003c/p\u003e\n\u003cp style=\"color: #856a5d;\"\u003eThe benefits of learning cognitive science and related academic fields are not only to be able to understand human mental processes and behaviors scientifically, but to help create effective solutions to various problems in modern society and industry. \u003cbr\u003eThis course aims to learn the essential literacy to apply such knowledge effectively and creatively to solve real-world problems that you will face in the future.\u003cbr\u003e\u003cbr\u003eIn this year’s course, we will focus on four topics from numerous studies related to cognitive science:\u003cbr\u003e(1) Affordances and Signifiers,\u003cbr\u003e(2) Visual Perception,\u003cbr\u003e(3) Decision-Making and Cognitive Biases, and\u003cbr\u003e(4) Motivation and Behavior Change.\u003cbr\u003e\u003cbr\u003eI will explain the theoretical foundations of each topic, and then we will review and discuss the usefulness and the issues of their practical applications, especially in the fields of design and marketing, with the help of case studies.\u003cbr\u003e\u003cbr\u003eThis course particularly welcomes students who have a strong interest and passion for practical applications of academic knowledge.\u003cbr\u003e\u003c/p\u003e\n\n\u003ch3 style=\"background-color: #394B58; color: white; padding-left: 8px; margin-bottom: 0; font-weight: bold;\"\u003e授業シラバス\u003c/h3\u003e\n\u003ch4 style=\"background-color: #ccecff; padding-left: 8px; margin-top: 0; font-weight: bold;\"\u003e主題と目標／授業の手法など\u003c/h4\u003e\n\u003cp\u003eこの授業では、認知科学、及びその関連研究や実世界における事例を通じて以下の点について学びます。\u003cbr\u003e\u003cbr\u003e・産業・社会における実践と認知科学、及びその関連研究との関連性\u003cbr\u003e\u003cbr\u003e・実世界の問題解決における、認知科学、及びその関連研究の有用性\u003cbr\u003e\u003cbr\u003e・実践的応用における基本的な考え方やアプローチ、留意点、困難や限界\u003cbr\u003e\u003cbr\u003e以上の学習を通じ、将来直面するであろう実際の問題解決において、認知科学、及びその関連研究の知識を効果的かつ適切に応用しうる素養の獲得を目指します。\u003cbr\u003e\u003cbr\u003e\u003cbr\u003e授業は週ごとに異なるトピックを設定します。\u003cbr\u003e\u003cbr\u003e第１週は授業の概要を説明した後、本授業の内容をより良く理解する上で必要な関連概念について紹介します。\u003cbr\u003e\u003cbr\u003e第２週から第５週は、それぞれアフォーダンスとシグニファイア、視知覚、意思決定と認知バイアス、モチベーションと行動変容をトピックとして取り上げ、授業を行います。各週、前半では理論的な基礎を紹介し、後半ではデザインやマーケティングなど、実社会における応用事例を取り上げ、学術的な視点からケーススタディを行います。この間、課題として個別にケーススタディを実施していただきます。\u003cbr\u003e\u003cbr\u003e最終週は「デザイン批評セッション」を行う予定で、受講者によるプレゼンテーションやディスカッションを行います。\u003cbr\u003e\u003cbr\u003e授業は対話的に行う予定です。特にケーススタディ、及びプレゼンテーションでは積極的な参与を求めます。\u003c/p\u003e\n\u003cp style=\"color: #856a5d;\"\u003eIn this course, we will learn the following points through related researches in cognitive science and real-world examples:\u003cbr\u003e\u003cbr\u003e -The relevance between related researches in cognitive science and practices in modern society and industry\u003cbr\u003e\u003cbr\u003e -The usefulness of related researches in cognitive science in solving real-world problems\u003cbr\u003e\u003cbr\u003e -Fundamental concepts, approaches, considerations, difficulties, and limitations in practical applications\u003cbr\u003e\u003cbr\u003eThrough the above-mentioned, we aim to acquire the essential literacy to apply related researches in cognitive science effectively and appropriately in order to solve real-world problems that you will face in the future.\u003cbr\u003e\u003cbr\u003e\u003cbr\u003eThis course is set up with different topics each week.\u003cbr\u003e\u003cbr\u003eOn week 1, we will go through the overview of this course. Then, I will illustrate the relevant concepts, which are needed to better understand the contents of the course.\u003cbr\u003e\u003cbr\u003eOn weeks 2-5, we will focus on the following topics respectively:\u003cbr\u003e- Affordances and Signifiers\u003cbr\u003e- Visual Perception\u003cbr\u003e- Decision-Making and Cognitive Biases\u003cbr\u003e- Motivation and Behavior Change\u003cbr\u003e\u003cbr\u003eThe first half of the lectures introduce the theoretical foundations of each concept. The second half reviews and discusses applied examples in real-world such as design and marketing fields. We will conduct case studies from a scientific perspective. In parallel with the activities, individual case studies will be given as assignments during this period.\u003cbr\u003e\u003cbr\u003eIn the final week of the course, \"Design Critique Session\" will be conducted including scheduled student presentations and Q\u0026amp;A portions.\u003cbr\u003e\u003cbr\u003eThis course takes an interactive lecture format. Students will be required to participate actively in the course, especially during the case studies and presentations.\u003cbr\u003e\u003c/p\u003e\n\n\u003ch4 style=\"background-color: #ccecff; padding-left: 8px; font-weight: bold;\"\u003e教材・参考文献\u003c/h4\u003e\n\u003cp\u003e・D. A. ノーマン (著), 岡本明 (翻訳), 安村通晃 (翻訳), 伊賀聡一郎 (翻訳), 野島久雄 (翻訳). 誰のためのデザイン？　増補・改訂版　―認知科学者のデザイン原論. 新曜社, 2015, 520p\u003cbr\u003e\u003cbr\u003e・ダニエル・カーネマン  (著), 村井章子 (翻訳). ファスト\u0026amp;スロー(上) あなたの意思はどのように決まるか?，早川書房，2014, 448p\u003cbr\u003e\u003cbr\u003e・ダニエル・カーネマン  (著), 村井章子 (翻訳). ファスト\u0026amp;スロー(下) あなたの意思はどのように決まるか?，早川書房，2014, 432p\u003cbr\u003e\u003cbr\u003e・リチャード・セイラー  (著), キャス・サンスティーン (著), 遠藤 真美 (翻訳)．実践 行動経済学，日経BP，2009，416p\u003cbr\u003e\u003cbr\u003e・黒須 正明 (著, 編集)．人間中心設計の基礎 (HCDライブラリー (第1巻)) ，近代科学社，2013，296p\u003cbr\u003e\u003cbr\u003e・原田 悦子 (著)．人の視点からみた人工物研究 (認知科学モノグラフ 6)，共立出版，1997，230p\u003c/p\u003e\n\n\u003ch4 style=\"background-color: #ccecff; padding-left: 8px; font-weight: bold;\"\u003e提出課題・試験・成績評価の方法など\u003c/h4\u003e\n\u003cp\u003e成績評価は以下のように行います。\u003cbr\u003e・授業への積極的な参与 30%\u003cbr\u003e・ケーススタディ課題 40%\u003cbr\u003e・プレゼンテーション 30%\u003cbr\u003e\u003c/p\u003e\n\u003cp style=\"color: #856a5d;\"\u003eThe course grade will be calculated as follows:\u003cbr\u003e1. Class participation - 30%\u003cbr\u003e2. Individual case studies - 40%\u003cbr\u003e3. End of term presentation - 30%\u003cbr\u003e\u003c/p\u003e\n\n\u003ch4 style=\"background-color: #ccecff; padding-left: 8px; font-weight: bold;\"\u003e履修上の注意\u003c/h4\u003e\n\u003cp\u003e授業の内容は受講者の要望や社会の状況に応じて変更される場合があります。\u003c/p\u003e\n\u003cp style=\"color: #856a5d;\"\u003eThe contents of this course are subject to change depending on the requests of students and social situations.\u003c/p\u003e\n\n\n\u003ch4 style=\"background-color: #ccecff; padding-left: 8px; font-weight: bold;\"\u003e授業計画\u003c/h4\u003e\n  \u003cp\u003e\n  \u003cu\u003e第1回 概要\u003c/u\u003e\n    \u003cbr\u003e\n    \u003cspan style=\"color: #856a5d;\"\u003e[Course Overview]\u003c/span\u003e\n  \u003c/p\u003e\n  \u003cp\u003e\n  \u003c/p\u003e\u003cp\u003e・授業のコンセプト\u003cbr\u003e・目的\u003cbr\u003e・計画\u003cbr\u003e・成績評価\u003cbr\u003e\u003c/p\u003e\n  \u003cp style=\"color: #856a5d;\"\u003e- Concept of this course\u003cbr\u003e- Objectives\u003cbr\u003e- Plan\u003cbr\u003e- Grading\u003cbr\u003e\u003c/p\u003e\n  \n  \u003cp\u003e  \u003c/p\u003e\n  \u003chr\u003e\n  \u003cp\u003e\n  \u003cu\u003e第2回 導入\u003c/u\u003e\n    \u003cbr\u003e\n    \u003cspan style=\"color: #856a5d;\"\u003e[Introduction]\u003c/span\u003e\n  \u003c/p\u003e\n  \u003cp\u003e\n  \u003c/p\u003e\u003cp\u003e・現実とは何か\u003cbr\u003e・メンタルモデルと概念モデル\u003cbr\u003e・認知科学、及び関連研究は実世界の問題解決においてどう役立つのか\u003cbr\u003e・ユーザ/カスタマーエクスペリエンスと人間中心設計\u003cbr\u003e・知覚品質\u003cbr\u003e・研究倫理\u003cbr\u003e\u003c/p\u003e\n  \u003cp style=\"color: #856a5d;\"\u003e- What is reality?\u003cbr\u003e- Mental and conceptual models\u003cbr\u003e- How can related researches in cognitive science be useful in solving real-world problems?\u003cbr\u003e- User/Consumer Experience and Human-Centered Design\u003cbr\u003e- Perceived quality\u003cbr\u003e- Research ethics\u003c/p\u003e\n  \n  \u003cp\u003e  \u003c/p\u003e\n  \u003chr\u003e\n  \u003cp\u003e\n  \u003cu\u003e第3回 アフォーダンスとシグニファイア（基礎）\u003c/u\u003e\n    \u003cbr\u003e\n    \u003cspan style=\"color: #856a5d;\"\u003e[Affordances and Signifiers - Theoretical Foundation]\u003c/span\u003e\n  \u003c/p\u003e\n  \u003cp\u003e\n  \u003c/p\u003e\u003cp\u003e・アフォーダンス・シグニファイアとは何か\u003cbr\u003e・なぜこれらの概念が重要なのか\u003cbr\u003e・日常生活における事例\u003c/p\u003e\n  \u003cp style=\"color: #856a5d;\"\u003e- What are affordances and signifiers?\u003cbr\u003e- Why are these concepts important? \u003cbr\u003e- Examples in everyday life\u003cbr\u003e\u003c/p\u003e\n  \n  \u003cp\u003e  \u003c/p\u003e\n  \u003chr\u003e\n  \u003cp\u003e\n  \u003cu\u003e第4回 アフォーダンスとシグニファイア（応用）\u003c/u\u003e\n    \u003cbr\u003e\n    \u003cspan style=\"color: #856a5d;\"\u003e[Affordances and Signifiers \u0026amp;#8211; Examples of Applications]\u003c/span\u003e\n  \u003c/p\u003e\n  \u003cp\u003e\n  \u003c/p\u003e\u003cp\u003e・応用事例の紹介\u003cbr\u003e・ケーススタディ\u003cbr\u003e※可能ならフィールドワークを実施予定\u003cbr\u003e\u003c/p\u003e\n  \u003cp style=\"color: #856a5d;\"\u003e- Practical examples in industry and society\u003cbr\u003e- Case studies\u003cbr\u003e- Fieldworks (if possible)\u003cbr\u003e\u003c/p\u003e\n  \n  \u003cp\u003e  \u003c/p\u003e\n  \u003chr\u003e\n  \u003cp\u003e\n  \u003cu\u003e第5回 視知覚（基礎）\u003c/u\u003e\n    \u003cbr\u003e\n    \u003cspan style=\"color: #856a5d;\"\u003e[Visual Perception - Theoretical Foundation]\u003c/span\u003e\n  \u003c/p\u003e\n  \u003cp\u003e\n  \u003c/p\u003e\u003cp\u003e・目の構造\u003cbr\u003e・視知覚のメカニズム\u003cbr\u003e・近年の研究\u003cbr\u003e\u003c/p\u003e\n  \u003cp style=\"color: #856a5d;\"\u003e- Structure of the human eye\u003cbr\u003e- Mechanism of visual perception\u003cbr\u003e- Some recent researches\u003cbr\u003e\u003c/p\u003e\n  \n  \u003cp\u003e  \u003c/p\u003e\n  \u003chr\u003e\n  \u003cp\u003e\n  \u003cu\u003e第6回 視知覚（応用）\u003c/u\u003e\n    \u003cbr\u003e\n    \u003cspan style=\"color: #856a5d;\"\u003e[Visual Perception \u0026amp;#8211; Examples of Applications]\u003c/span\u003e\n  \u003c/p\u003e\n  \u003cp\u003e\n  \u003c/p\u003e\u003cp\u003e・応用事例の紹介\u003cbr\u003e・ケーススタディ\u003c/p\u003e\n  \u003cp style=\"color: #856a5d;\"\u003e- Practical examples in industry and society\u003cbr\u003e- Case studies\u003cbr\u003e\u003c/p\u003e\n  \n  \u003cp\u003e  \u003c/p\u003e\n  \u003chr\u003e\n  \u003cp\u003e\n  \u003cu\u003e第7回 意思決定と認知バイアス（基礎）\u003c/u\u003e\n    \u003cbr\u003e\n    \u003cspan style=\"color: #856a5d;\"\u003e[Decision-Making and Cognitive Biases - Theoretical Foundation]\u003c/span\u003e\n  \u003c/p\u003e\n  \u003cp\u003e\n  \u003c/p\u003e\u003cp\u003e・認知バイアスとは何か\u003cbr\u003e・システム１とシステム２\u003cbr\u003e・何故認知バイアスが重要なのか\u003cbr\u003e・様々な認知バイアスの事例\u003cbr\u003e\u003c/p\u003e\n  \u003cp style=\"color: #856a5d;\"\u003e- What are cognitive biases?\u003cbr\u003e- System 1 and System 2\u003cbr\u003e- Why are cognitive biases important?\u003cbr\u003e- Examples of various cognitive biases\u003cbr\u003e\u003c/p\u003e\n  \n  \u003cp\u003e  \u003c/p\u003e\n  \u003chr\u003e\n  \u003cp\u003e\n  \u003cu\u003e第8回 意思決定と認知バイアス（応用）\u003c/u\u003e\n    \u003cbr\u003e\n    \u003cspan style=\"color: #856a5d;\"\u003e[Decision-Making and Cognitive Biases - Examples of Applications]\u003c/span\u003e\n  \u003c/p\u003e\n  \u003cp\u003e\n  \u003c/p\u003e\u003cp\u003e・応用事例の紹介\u003cbr\u003e・ケーススタディ\u003c/p\u003e\n  \u003cp style=\"color: #856a5d;\"\u003e- Practical examples in industry and society\u003cbr\u003e- Case studies\u003cbr\u003e\u003c/p\u003e\n  \n  \u003cp\u003e  \u003c/p\u003e\n  \u003chr\u003e\n  \u003cp\u003e\n  \u003cu\u003e第9回 モチベーションと行動変容（基礎）\u003c/u\u003e\n    \u003cbr\u003e\n    \u003cspan style=\"color: #856a5d;\"\u003e[Motivation and Behavior Change - Theoretical Foundation]\u003c/span\u003e\n  \u003c/p\u003e\n  \u003cp\u003e\n  \u003c/p\u003e\u003cp\u003e・人々が行動を起こす動機\u003cbr\u003e・何故モチベーションや行動変容が重要なのか\u003cbr\u003e・モチベーションに関する関連研究\u003cbr\u003e・行動変容に関するモデル\u003cbr\u003e\u003c/p\u003e\n  \u003cp style=\"color: #856a5d;\"\u003e- What motivates people to take action\u003cbr\u003e- Why are these studies important?\u003cbr\u003e- Related Researches in Motivation\u003cbr\u003e- Models Regarding Behavioral Change\u003cbr\u003e\u003c/p\u003e\n  \n  \u003cp\u003e  \u003c/p\u003e\n  \u003chr\u003e\n  \u003cp\u003e\n  \u003cu\u003e第10回 モチベーションと行動変容（応用）\u003c/u\u003e\n    \u003cbr\u003e\n    \u003cspan style=\"color: #856a5d;\"\u003e[Motivation and Behavior Change - Examples of Applications]\u003c/span\u003e\n  \u003c/p\u003e\n  \u003cp\u003e\n  \u003c/p\u003e\u003cp\u003e・応用事例の紹介\u003cbr\u003e・ケーススタディ\u003c/p\u003e\n  \u003cp style=\"color: #856a5d;\"\u003e- Practical examples in industry and society\u003cbr\u003e- Case studies\u003cbr\u003e\u003c/p\u003e\n  \n  \u003cp\u003e  \u003c/p\u003e\n  \u003chr\u003e\n  \u003cp\u003e\n  \u003cu\u003e第11回 デザイン批評セッション１\u003c/u\u003e\n    \u003cbr\u003e\n    \u003cspan style=\"color: #856a5d;\"\u003e[Design Critique Session #1]\u003c/span\u003e\n  \u003c/p\u003e\n  \u003cp\u003e\n  \u003c/p\u003e\u003cp\u003e・プレゼンテーション\u003cbr\u003e・Q\u0026amp;A\u003cbr\u003e・コメント\u003c/p\u003e\n  \u003cp style=\"color: #856a5d;\"\u003ePresentations, Q\u0026amp;A portions, and feedbacks\u003c/p\u003e\n  \n  \u003cp\u003e  \u003c/p\u003e\n  \u003chr\u003e\n  \u003cp\u003e\n  \u003cu\u003e第12回 デザイン批評セッション２\u003c/u\u003e\n    \u003cbr\u003e\n    \u003cspan style=\"color: #856a5d;\"\u003e[Design Critique Session #2]\u003c/span\u003e\n  \u003c/p\u003e\n  \u003cp\u003e\n  \u003c/p\u003e\u003cp\u003e・プレゼンテーション\u003cbr\u003e・Q\u0026amp;A\u003cbr\u003e・コメント\u003cbr\u003e・振り返り\u003c/p\u003e\n  \u003cp style=\"color: #856a5d;\"\u003e- Presentations, Q\u0026amp;A portions, and feedbacks\u003cbr\u003e- Review of this course\u003c/p\u003e\n  \n  \u003cp\u003e  \u003c/p\u003e\n  \u003chr\u003e\n  \u003cp\u003e\n  \u003cu\u003e第13回 ケーススタディ課題\u003c/u\u003e\n    \u003cbr\u003e\n    \u003cspan style=\"color: #856a5d;\"\u003e[Assignments for Case Studies]\u003c/span\u003e\n  \u003c/p\u003e\n  \u003cp\u003e\n  \u003c/p\u003e\u003cp\u003e\u003c/p\u003e\n  \u003cp style=\"color: #856a5d;\"\u003e\u003c/p\u003e\n  \n  \u003cp\u003e  \u003c/p\u003e\n  \u003chr\u003e\n  \u003cp\u003e\n  \u003cu\u003e第14回 ケーススタディ課題\u003c/u\u003e\n    \u003cbr\u003e\n    \u003cspan style=\"color: #856a5d;\"\u003e[Assignments for Case Studies]\u003c/span\u003e\n  \u003c/p\u003e\n  \u003cp\u003e\n  \u003c/p\u003e\u003cp\u003e\u003c/p\u003e\n  \u003cp style=\"color: #856a5d;\"\u003e\u003c/p\u003e\n  \n  \u003cp\u003e  \u003c/p\u003e\n  \u003chr\u003e\n  \u003cp\u003e\n  \u003cu\u003e第15回 プレゼンテーションの準備\u003c/u\u003e\n    \u003cbr\u003e\n    \u003cspan style=\"color: #856a5d;\"\u003e[Preparation of the Presentation]\u003c/span\u003e\n  \u003c/p\u003e\n  \u003cp\u003e\n  \u003c/p\u003e\u003cp\u003e\u003c/p\u003e\n  \u003cp style=\"color: #856a5d;\"\u003e\u003c/p\u003e\n  \n  \u003cp\u003e  \u003c/p\u003e\n  \u003chr\u003e\n\n  \u003cu\u003e15回目に相当するその他の授業計画\u003c/u\u003e\u003cbr\u003e\n  \u003cp\u003e\u003c/p\u003e\n  \u003cp style=\"color: #856a5d;\"\u003e\u003c/p\u003e\n","course_code":"応用認知科学","default_view":"modules","root_account_id":1,"enrollment_term_id":3,"license":null,"grade_passback_setting":null,"end_at":null,"public_syllabus":false,"public_syllabus_to_auth":true,"storage_quota_mb":30000,"is_public_to_auth_users":true,"term":{"id":3,"name":"2020年秋学期","start_at":null,"end_at":null,"created_at":"2020-09-03T21:25:41Z","workflow_state":"active","grading_period_group_id":null},"apply_assignment_group_weights":false,"calendar":{"ics":"https://sol.sfc.keio.ac.jp/feeds/calendars/course_7QgLCz2EFj2aBEPVx17DidtR6nWm6KK8K9Idbkoe.ics"},"time_zone":"Asia/Tokyo","blueprint":false,"enrollments":[],"hide_final_grades":false,"workflow_state":"available","restrict_enrollments_to_course_dates":false,"overridden_course_visibility":""}