{"id":1178,"name":"新事業創造ワークショップ / WORKSHOPS ON NEW BUSINESS CREATION","account_id":1,"uuid":"Lvhn57OS9925I8pmnxfx7qvoASqtfhCc1atYWva9","start_at":null,"grading_standard_id":null,"is_public":false,"created_at":"2020-10-01T04:40:34Z","syllabus_body":"\u003ctable style=\"width: 100%; margin: 0; border-collapse: collapse; background-color: #394B58; color: white;\" border=\"1\"\u003e\n  \u003ctbody\u003e\n      \u003ctr\u003e\n        \u003ctd style=\"width: 50%;\"\u003e\n          B6004\u003cbr\u003e\n          新事業創造ワークショップ\u003cbr\u003e\n          \u003cspan style=\"color: #c9c9c9;\"\u003eWORKSHOPS ON NEW BUSINESS CREATION\u003c/span\u003e\n        \u003c/td\u003e\n        \u003ctd\u003e\n          創造実践科目\u003cbr\u003e\n          \u003cspan style=\"color: #c9c9c9;\"\u003eCreative Courses (Practice)\u003c/span\u003e\u003cbr\u003e\n          2 単位\n        \u003c/td\u003e\n      \u003c/tr\u003e\n  \u003c/tbody\u003e\n\u003c/table\u003e\n\n\u003ctable style=\"width: 100%; margin: 0; border-collapse: collapse; border: 1px solid #C7CDD1;\" border=\"1\"\u003e\n  \u003ctbody\u003e\n    \u003ctr\u003e\n      \u003ctd style=\"width: 25%; background-color: #F5F5F5; border-color: #C7CDD1;\"\u003e実施形態\u003c/td\u003e\n      \u003ctd style=\"border-color: #C7CDD1;\"\u003e完全オンライン\u003c/td\u003e\n    \u003c/tr\u003e\n    \u003ctr\u003e\n      \u003ctd style=\"background-color: #F5F5F5; border-color: #C7CDD1;\"\u003e開催日程\u003c/td\u003e\n      \u003ctd style=\"border-color: #C7CDD1;\"\u003e秋学期 木曜日２時限\u003c/td\u003e\n    \u003c/tr\u003e\n    \u003ctr\u003e\n      \u003ctd style=\"background-color: #F5F5F5; border-color: #C7CDD1;\"\u003e担当教員\u003c/td\u003e\n      \u003ctd style=\"border-color: #C7CDD1;\"\u003e鈴木 寛:矢作 尚久:山本 雄士（スズキ カン:ヤハギ ナオヒサ:ヤマモト ユウジ）\u003c/td\u003e\n    \u003c/tr\u003e\n    \u003ctr\u003e\n      \u003ctd style=\"background-color: #F5F5F5; border-color: #C7CDD1;\"\u003e関連科目\u003c/td\u003e\n      \u003ctd style=\"border-color: #C7CDD1;\"\u003e\n          前提科目（推奨）: B6032\u003cbr\u003e\n          前提科目（関連）: 64260,B6054,C1032,60270\u003cbr\u003e\n      \u003c/td\u003e\n    \u003c/tr\u003e\n    \u003ctr\u003e\n      \u003ctd style=\"background-color: #F5F5F5; border-color: #C7CDD1;\"\u003e開講場所\u003c/td\u003e\n      \u003ctd style=\"border-color: #C7CDD1;\"\u003eSFC\u003c/td\u003e\n    \u003c/tr\u003e\n    \u003ctr\u003e\n      \u003ctd style=\"background-color: #F5F5F5; border-color: #C7CDD1;\"\u003e授業形態\u003c/td\u003e\n      \u003ctd style=\"border-color: #C7CDD1;\"\u003e講義、実習・演習、グループワーク\u003c/td\u003e\n    \u003c/tr\u003e\n    \u003ctr\u003e\n      \u003ctd style=\"background-color: #F5F5F5; border-color: #C7CDD1;\"\u003e履修者制限\u003c/td\u003e\n      \u003ctd style=\"border-color: #C7CDD1;\"\u003e\n          \u003cp\u003e履修人数を制限する\u003cbr\u003e\u003cbr\u003e受入学生数（予定）：約 15 人\u003cbr\u003e選抜方法：システムによる選抜（抽選）\u003cbr\u003e\u003cbr\u003e◯エントリー〆切日時：2020年9月28日（月） 17:00\u003cbr\u003e◯履修許可者発表日時：2020年9月30日（水） 17:00\u003cbr\u003e\u003cbr\u003e\u003c/p\u003e\n          \u003cp style=\"color: #856a5d;\"\u003eOnly the selected students can take this course.\u003cbr\u003e\u003cbr\u003eNumber of students in the class (scheduled) : About 15\u003cbr\u003eAutomatic Screening (Lottery)\u003cbr\u003e\u003cbr\u003e* Schedule: TBD\u003c/p\u003e\n      \u003c/td\u003e\n    \u003c/tr\u003e\n    \u003ctr\u003e\n      \u003ctd style=\"background-color: #F5F5F5; border-color: #C7CDD1;\"\u003e履修条件\u003c/td\u003e\n      \u003ctd style=\"border-color: #C7CDD1;\"\u003e\n        \u003cp\u003e\u003c/p\u003e\n        \u003cp style=\"color: #856a5d;\"\u003e\u003c/p\u003e\n        \u003cp\u003e一年生の履修は基本的には勧めない。\u003cbr\u003e\u003cbr\u003e新事業創造に強い関心と意欲をもっていること。\u003cbr\u003e何らかのプロジェクトを立ち上げる意志があること。\u003cbr\u003e\u003cbr\u003e履修者人数は１５名程度を想定。\u003c/p\u003e\n        \u003cp style=\"color: #856a5d;\"\u003eBasically, we won’t recommend 1st graders to take the course.\u003cbr\u003e\u003c/p\u003e\n      \u003c/td\u003e\n    \u003c/tr\u003e\n    \u003ctr\u003e\n      \u003ctd style=\"background-color: #F5F5F5; border-color: #C7CDD1;\"\u003e使用言語\u003c/td\u003e\n      \u003ctd style=\"border-color: #C7CDD1;\"\u003e英語\u003c/td\u003e\n    \u003c/tr\u003e\n    \u003ctr\u003e\n      \u003ctd style=\"background-color: #F5F5F5; border-color: #C7CDD1;\"\u003e連絡先\u003c/td\u003e\n      \u003ctd style=\"border-color: #C7CDD1;\"\u003esuzukan0001@hotmail.com\u003c/td\u003e\n    \u003c/tr\u003e\n    \u003ctr\u003e\n      \u003ctd style=\"background-color: #F5F5F5; border-color: #C7CDD1;\"\u003e授業ホームページ\u003c/td\u003e\n      \u003ctd style=\"border-color: #C7CDD1;\"\u003e\u003c/td\u003e\n    \u003c/tr\u003e\n    \u003ctr\u003e\n      \u003ctd style=\"background-color: #F5F5F5; border-color: #C7CDD1;\"\u003e同一科目\u003c/td\u003e\n      \u003ctd style=\"border-color: #C7CDD1;\"\u003e\n        \u003cp\u003e\u003c/p\u003e\n        \u003cp style=\"color: #856a5d;\"\u003e\u003c/p\u003e\n      \u003c/td\u003e\n    \u003c/tr\u003e\n    \u003ctr\u003e\n      \u003ctd style=\"background-color: #F5F5F5; border-color: #C7CDD1;\"\u003e学生が利用する予定機材/ソフト等\u003c/td\u003e\n      \u003ctd style=\"border-color: #C7CDD1;\"\u003e\n        \u003cp\u003e\u003c/p\u003e\n        \u003cp style=\"color: #856a5d;\"\u003e\u003c/p\u003e\n      \u003c/td\u003e\n    \u003c/tr\u003e\n    \u003ctr\u003e\n      \u003ctd style=\"background-color: #F5F5F5; border-color: #C7CDD1;\"\u003e設置学部・研究科\u003c/td\u003e\n      \u003ctd style=\"border-color: #C7CDD1;\"\u003e総合政策・環境情報学部\u003c/td\u003e\n    \u003c/tr\u003e\n    \u003ctr\u003e\n      \u003ctd style=\"background-color: #F5F5F5; border-color: #C7CDD1;\"\u003e大学院プロジェクト名\u003c/td\u003e\n      \u003ctd style=\"border-color: #C7CDD1;\"\u003e\u003cp style=\"color: #856a5d;\"\u003e\u003c/p\u003e\u003c/td\u003e\n    \u003c/tr\u003e\n    \u003ctr\u003e\n      \u003ctd style=\"background-color: #F5F5F5; border-color: #C7CDD1;\"\u003e大学院プロジェクトサブメンバー\u003c/td\u003e\n      \u003ctd style=\"border-color: #C7CDD1;\"\u003e\n        \u003cp\u003e\u003c/p\u003e\n        \u003cp style=\"color: #856a5d;\"\u003e\u003c/p\u003e\n      \u003c/td\u003e\n    \u003c/tr\u003e\n    \u003ctr\u003e\n      \u003ctd style=\"background-color: #F5F5F5; border-color: #C7CDD1;\"\u003eゲストスピーカーの人数\u003c/td\u003e\n      \u003ctd style=\"border-color: #C7CDD1;\"\u003e0\u003c/td\u003e\n    \u003c/tr\u003e\n    \u003ctr\u003e\n      \u003ctd style=\"background-color: #F5F5F5; border-color: #C7CDD1;\"\u003e履修選抜・課題タイプ=テキスト登録可\u003c/td\u003e\n      \u003ctd style=\"border-color: #C7CDD1;\"\u003efalse\u003c/td\u003e\n    \u003c/tr\u003e\n    \u003ctr\u003e\n      \u003ctd style=\"background-color: #F5F5F5; border-color: #C7CDD1;\"\u003e履修選抜・選抜課題タイプ=ファイル登録可\u003c/td\u003e\n      \u003ctd style=\"border-color: #C7CDD1;\"\u003efalse\u003c/td\u003e\n    \u003c/tr\u003e\n    \u003ctr\u003e\n      \u003ctd style=\"background-color: #F5F5F5; border-color: #C7CDD1;\"\u003eGIGAサティフィケート対象\u003c/td\u003e\n      \u003ctd style=\"border-color: #C7CDD1;\"\u003etrue\u003c/td\u003e\n    \u003c/tr\u003e\n    \u003ctr\u003e\n      \u003ctd style=\"background-color: #F5F5F5; border-color: #C7CDD1;\"\u003e最終更新日\u003c/td\u003e\n      \u003ctd style=\"border-color: #C7CDD1;\"\u003e2020/08/26 14:56:16\u003c/td\u003e\n    \u003c/tr\u003e\n  \u003c/tbody\u003e\n\u003c/table\u003e\n\n\n\n\n\u003ch3 style=\"background-color: #394B58; color: white; padding-left: 8px; font-weight: bold;\"\u003e科目概要\u003c/h3\u003e\n\n\u003cp\u003e Project structure in  the information society is changing radically. Today, we have to start up various projects with social significance under the progressively diversifying sense of values. This class aims to master news way to create project through practice.\u003cbr\u003e Firstly, we will deepen the understanding of information editing, gathering, investigation, evaluation, articulation, synthesis and expression. Then, we will understand the process of grasping total trend such as historical background and social background, vivifying awareness of the problem as the person concerned, gathering various features such as needs and new seeds of specific community, and creating new trends and practices by putting together those features. By utilizing these frameworks and developing projects, we aim to brush up practical skills.\u003c/p\u003e\n\u003cp style=\"color: #856a5d;\"\u003e工業社会における事業構築と情報社会における事業創造のあり様は劇的に変化している。\u003cbr\u003e価値観が多様化が急速に進展し、様々な社会的意義のあるプロジェクトを立ち上げていかねばならない今日、新たな事業創造の方法を実践を通じて体得することを目的とする。\u003cbr\u003e\u003cbr\u003e具体的には、まず、情報編集の方法、情報の収集、精査、評価、結合、総合、表現について理解を深める。そして、時代背景、社会背景など、大きな流れを把握した上で、当事者としての問題意識を鮮明にし、特定のコミュニティのニーズ、新たなシーズといった様々な要素を収集し、それらを構成することによって、新たな流れ、動きを創造していく、こうしたプロセスを理論的に理解するとともに、そうした枠組みを活用しながら、実際に事業を考案・構想していくことを通じて、実践力をみがいていく。\u003c/p\u003e\n\n\u003ch3 style=\"background-color: #394B58; color: white; padding-left: 8px; margin-bottom: 0; font-weight: bold;\"\u003e授業シラバス\u003c/h3\u003e\n\u003ch4 style=\"background-color: #ccecff; padding-left: 8px; margin-top: 0; font-weight: bold;\"\u003e主題と目標／授業の手法など\u003c/h4\u003e\n\u003cp\u003e具体的な新事業を構想できる人財に成長することを目的として、\u003cbr\u003e\u003cbr\u003e①新事業創造の基本的な手法・プロセスについて理解する。(講義・熟議ワーク)\u003cbr\u003e②新事業創造にあたって、現在の時代背景、社会背景、技術動向を把握する。(資料調査報告)\u003cbr\u003e③今を生きる当事者として、それぞれの問題意識を顕在化させる。(レポート 熟議ワーク)\u003cbr\u003e④新事業創造にあたって、ニーズとシーズを探る。(資料調査・熟議ワーク)\u003cbr\u003e⑤新事業創造にとって必要なルール・ロール・ツールを構想・構想する。(熟議ワーク)\u003cbr\u003e⑥新事業創造のソーシャル・ビジネスモデルとハイパーサイクルを考案・構想する。(熟議ワーク)\u003cbr\u003e⑦新事業創造にあたってのボトルネック、ディレンマ、コンフリクト、トレードオフを\u003cbr\u003e把握し、その対応策を考案する。(資料調査、熟議ワーク)\u003cbr\u003e⑧新事業案をまとめ発表する。\u003c/p\u003e\n\u003cp style=\"color: #856a5d;\"\u003eWe aim to develop talents able to create new projects and\u003cbr\u003e\u003cbr\u003e①Understand basic methods and process of new project creation. (Lecture and deliberative work)\u003cbr\u003e②Grasp current historical background, social background and technological trends.(Investigation and report of resources)\u003cbr\u003e③As the person concerned, actualize the awareness of the problem. (Report and deliberative work)\u003cbr\u003e④Investigate the needs and seeds. (Resource research and deliberative work)\u003cbr\u003e⑤Develop the rule, role and tools necessary to create new projects. (Deliberative work)\u003cbr\u003e⑥Develop the model of social business and hyper-cycle. (Deliberative work)\u003cbr\u003e⑦Grasp bottleneck, dilemma, conflict and trade-off in creating the new projects and develop the countermeasure (Deliberative work).\u003cbr\u003e⑧Make the presentation of new project plan.\u003cbr\u003e\u003c/p\u003e\n\n\u003ch4 style=\"background-color: #ccecff; padding-left: 8px; font-weight: bold;\"\u003e教材・参考文献\u003c/h4\u003e\n\u003cp\u003e松岡正剛 編集工学研究所 「情報の歴史」 NTT出版 1996 P449\u003cbr\u003e松岡正剛 「知の編集術」 講談社現代新書 2000 p264\u003cbr\u003e松岡正剛 「知の編集工学」 朝日文庫 2001 p346\u003cbr\u003e\u003cbr\u003e野中郁次郎 「イノベーションの作法」日経ビジネス人文庫 2009 p352\u003cbr\u003e\u003cbr\u003eウッディーウェイド「 シナリオ・プランニング」英治出版 2013  P208\u003cbr\u003e米国国家情報会議 「２０３０年 世界はこう変わる アメリカ情報機関が分析した １７年後の未来」 講談社 2013 p202   \u003cbr\u003e英エコノミスト編集部 「２０５０年の世界 英エコノミスト誌は予想する」文芸春秋 2012 p429\u003cbr\u003eガルブレイス 「新盤 バブルの物語」 ダイヤモンド社 2008 p173\u003cbr\u003eランダース「2052 今後40年のグローバル予測」 日経BP 2013 p512\u003cbr\u003eフリードマン 「100年予想 世界最強のインテリジェンス企業が示す未来派遣地図」早川書房 2009 p381\u003cbr\u003eフリードマン 「激動予想;影のCIAが明かす近未来パワーバランス」早川書房 2011 p356\u003cbr\u003eミチオ・カク 「2100年の科学ライフ」 NHK出版 2012 p480\u003cbr\u003e馬場錬成 「ノーベル賞の100年 自然科学三賞でたどる科学史」 中公親書 2002 p239\u003cbr\u003eニッセイ基礎研究所「図解 20年後の日本」 日経新聞社出版社 2009 p232\u003cbr\u003e三浦展「データでわかる2030年の日本」洋泉社 2013 p205\u003cbr\u003e東京大学高齢社会総合研究機構 「2030年超高齢社会「ジェロントロジー」が日本を世界の中心にする 東洋経済新報社 2010 p213\u003cbr\u003e\u003cbr\u003e各省庁が発行する白書\u003c/p\u003e\n\n\u003ch4 style=\"background-color: #ccecff; padding-left: 8px; font-weight: bold;\"\u003e提出課題・試験・成績評価の方法など\u003c/h4\u003e\n\u003cp\u003e新事業プランを各自、または、グループで考案し、そのプランのクオリティにより評価する。\u003cbr\u003e提出物の提出状況および質が芳しくない場合は、単位取得に大いに影響があると心得ておくこと。\u003cbr\u003eまた、出席状況なども成績評価に加味する。\u003c/p\u003e\n\u003cp style=\"color: #856a5d;\"\u003eEvaluated based on the quality of plan developed by the individual or group. Keep in mind that if submission condition and quality of submitted report are poor, there will be significant effect to credit earning. Also, your attendance will effect your grade.\u003c/p\u003e\n\n\u003ch4 style=\"background-color: #ccecff; padding-left: 8px; font-weight: bold;\"\u003e履修上の注意\u003c/h4\u003e\n\u003cp\u003e15名程度を想定しています。\u003cbr\u003e\u003c/p\u003e\n\u003cp style=\"color: #856a5d;\"\u003eStudents are planning about 15 people.\u003c/p\u003e\n\n\n\u003ch4 style=\"background-color: #ccecff; padding-left: 8px; font-weight: bold;\"\u003e授業計画\u003c/h4\u003e\n  \u003cp\u003e\n  \u003cu\u003e第1回 Introduction\u003c/u\u003e\n  \u003c/p\u003e\n  \u003cp\u003e\n  \u003c/p\u003e\u003cp\u003eOrientation\u003c/p\u003e\n  \u003cp style=\"color: #856a5d;\"\u003e\u003c/p\u003e\n  \n  \u003cp\u003e  \u003c/p\u003e\n  \u003chr\u003e\n  \u003cp\u003e\n  \u003cu\u003e第2回 Lecture\u003c/u\u003e\n  \u003c/p\u003e\n  \u003cp\u003e\n  \u003c/p\u003e\u003cp\u003eoutline of project design\u003c/p\u003e\n  \u003cp style=\"color: #856a5d;\"\u003e\u003c/p\u003e\n  \n  \u003cp\u003e  \u003c/p\u003e\n  \u003chr\u003e\n  \u003cp\u003e\n  \u003cu\u003e第3回 Topics\u003c/u\u003e\n  \u003c/p\u003e\n  \u003cp\u003e\n  \u003c/p\u003e\u003cp\u003eFix project theme\u003c/p\u003e\n  \u003cp style=\"color: #856a5d;\"\u003e\u003c/p\u003e\n  \n  \u003cp\u003e  \u003c/p\u003e\n  \u003chr\u003e\n  \u003cp\u003e\n  \u003cu\u003e第4回 Whom will you make happy? \u003c/u\u003e\n  \u003c/p\u003e\n  \u003cp\u003e\n  \u003c/p\u003e\u003cp\u003eLecture   identification of social problem\u003c/p\u003e\n  \u003cp style=\"color: #856a5d;\"\u003e\u003c/p\u003e\n  \n  \u003cp\u003e  \u003c/p\u003e\n  \u003chr\u003e\n  \u003cp\u003e\n  \u003cu\u003e第5回 Disruptive Innovation \u0026amp; Dilemma of Innovation\u003c/u\u003e\n  \u003c/p\u003e\n  \u003cp\u003e\n  \u003c/p\u003e\u003cp\u003eLecture,  \u003cbr\u003eDisruptive Innovation \u0026amp; Dilemma of Innovation\u003c/p\u003e\n  \u003cp style=\"color: #856a5d;\"\u003e\u003c/p\u003e\n  \n  \u003cp\u003e  \u003c/p\u003e\n  \u003chr\u003e\n  \u003cp\u003e\n  \u003cu\u003e第6回 Social Resources \u0026amp; SWOT\u003c/u\u003e\n  \u003c/p\u003e\n  \u003cp\u003e\n  \u003c/p\u003e\u003cp\u003eIdentification of difficulties \u003cbr\u003eCheck of Social Resources\u003cbr\u003eSWOT Analysis\u003cbr\u003e\u003c/p\u003e\n  \u003cp style=\"color: #856a5d;\"\u003e\u003c/p\u003e\n  \n  \u003cp\u003e  \u003c/p\u003e\n  \u003chr\u003e\n  \u003cp\u003e\n  \u003cu\u003e第7回 Midterm Presentation\u003c/u\u003e\n  \u003c/p\u003e\n  \u003cp\u003e\n  \u003c/p\u003e\u003cp\u003e\u003c/p\u003e\n  \u003cp style=\"color: #856a5d;\"\u003e\u003c/p\u003e\n  \n  \u003cp\u003e  \u003c/p\u003e\n  \u003chr\u003e\n  \u003cp\u003e\n  \u003cu\u003e第8回 Midterm Presentation \u0026amp; Counsultation\u003c/u\u003e\n  \u003c/p\u003e\n  \u003cp\u003e\n  \u003c/p\u003e\u003cp\u003e\u003c/p\u003e\n  \u003cp style=\"color: #856a5d;\"\u003e\u003c/p\u003e\n  \n  \u003cp\u003e  \u003c/p\u003e\n  \u003chr\u003e\n  \u003cp\u003e\n  \u003cu\u003e第9回 Midterm Presentation \u0026amp; Consultation \u003c/u\u003e\n  \u003c/p\u003e\n  \u003cp\u003e\n  \u003c/p\u003e\u003cp\u003e\u003c/p\u003e\n  \u003cp style=\"color: #856a5d;\"\u003e\u003c/p\u003e\n  \n  \u003cp\u003e  \u003c/p\u003e\n  \u003chr\u003e\n  \u003cp\u003e\n  \u003cu\u003e第10回 Workshop\u003c/u\u003e\n  \u003c/p\u003e\n  \u003cp\u003e\n  \u003c/p\u003e\u003cp\u003e\u003c/p\u003e\n  \u003cp style=\"color: #856a5d;\"\u003e\u003c/p\u003e\n  \n  \u003cp\u003e  \u003c/p\u003e\n  \u003chr\u003e\n  \u003cp\u003e\n  \u003cu\u003e第11回 Final Presentation\u003c/u\u003e\n  \u003c/p\u003e\n  \u003cp\u003e\n  \u003c/p\u003e\u003cp\u003e\u003c/p\u003e\n  \u003cp style=\"color: #856a5d;\"\u003e\u003c/p\u003e\n  \n  \u003cp\u003e  \u003c/p\u003e\n  \u003chr\u003e\n  \u003cp\u003e\n  \u003cu\u003e第12回 Final Presentation\u003c/u\u003e\n  \u003c/p\u003e\n  \u003cp\u003e\n  \u003c/p\u003e\u003cp\u003e\u003c/p\u003e\n  \u003cp style=\"color: #856a5d;\"\u003e\u003c/p\u003e\n  \n  \u003cp\u003e  \u003c/p\u003e\n  \u003chr\u003e\n  \u003cp\u003e\n  \u003cu\u003e第13回 最終発表＋評価\u003c/u\u003e\n  \u003c/p\u003e\n  \u003cp\u003e\n  \u003c/p\u003e\u003cp\u003e\u003c/p\u003e\n  \u003cp style=\"color: #856a5d;\"\u003e\u003c/p\u003e\n  \n  \u003cp\u003e  \u003c/p\u003e\n  \u003chr\u003e\n  \u003cp\u003e\n  \u003cu\u003e第14回 最終発表+評価\u003c/u\u003e\n  \u003c/p\u003e\n  \u003cp\u003e\n  \u003c/p\u003e\u003cp\u003e\u003c/p\u003e\n  \u003cp style=\"color: #856a5d;\"\u003e\u003c/p\u003e\n  \n  \u003cp\u003e  \u003c/p\u003e\n  \u003chr\u003e\n  \u003cp\u003e\n  \u003cu\u003e第15回 最終発表＋評価\u003c/u\u003e\n  \u003c/p\u003e\n  \u003cp\u003e\n  \u003c/p\u003e\u003cp\u003e\u003c/p\u003e\n  \u003cp style=\"color: #856a5d;\"\u003e\u003c/p\u003e\n  \n  \u003cp\u003e  \u003c/p\u003e\n  \u003chr\u003e\n\n  \u003cu\u003e15回目に相当するその他の授業計画\u003c/u\u003e\u003cbr\u003e\n  \u003cp\u003eレポート提出 発表 熟議ワークへの参加をみて評価する\u003c/p\u003e\n  \u003cp style=\"color: #856a5d;\"\u003eEvaluated based on report submitted, presentation and participation to the deliberative works.\u003c/p\u003e\n","course_code":"新事業創造ワークショップ","default_view":"modules","root_account_id":1,"enrollment_term_id":3,"license":null,"grade_passback_setting":null,"end_at":null,"public_syllabus":false,"public_syllabus_to_auth":true,"storage_quota_mb":30000,"is_public_to_auth_users":true,"term":{"id":3,"name":"2020年秋学期","start_at":null,"end_at":null,"created_at":"2020-09-03T21:25:41Z","workflow_state":"active","grading_period_group_id":null},"apply_assignment_group_weights":false,"calendar":{"ics":"https://sol.sfc.keio.ac.jp/feeds/calendars/course_Lvhn57OS9925I8pmnxfx7qvoASqtfhCc1atYWva9.ics"},"time_zone":"Asia/Tokyo","blueprint":false,"enrollments":[],"hide_final_grades":false,"workflow_state":"available","restrict_enrollments_to_course_dates":false,"overridden_course_visibility":""}