{"id":910,"name":"インドネシア文化論 / INDONESIAN CULTURAL STUDIES","account_id":1,"uuid":"JSqH1QBTdOC4q462wEEufQIn4ZIgfLJIqQNx80MI","start_at":null,"grading_standard_id":null,"is_public":false,"created_at":"2020-10-01T04:40:17Z","syllabus_body":"\u003ctable style=\"width: 100%; margin: 0; border-collapse: collapse; background-color: #394B58; color: white;\" border=\"1\"\u003e\n  \u003ctbody\u003e\n      \u003ctr\u003e\n        \u003ctd style=\"width: 50%;\"\u003e\n          C1133\u003cbr\u003e\n          インドネシア文化論\u003cbr\u003e\n          \u003cspan style=\"color: #c9c9c9;\"\u003eINDONESIAN CULTURAL STUDIES\u003c/span\u003e\n        \u003c/td\u003e\n        \u003ctd\u003e\n          先端科目-総合政策系\u003cbr\u003e\n          \u003cspan style=\"color: #c9c9c9;\"\u003eAdvanced Subjects - Series of Policy Management\u003c/span\u003e\u003cbr\u003e\n          2 単位\n        \u003c/td\u003e\n      \u003c/tr\u003e\n  \u003c/tbody\u003e\n\u003c/table\u003e\n\n\u003ctable style=\"width: 100%; margin: 0; border-collapse: collapse; border: 1px solid #C7CDD1;\" border=\"1\"\u003e\n  \u003ctbody\u003e\n    \u003ctr\u003e\n      \u003ctd style=\"width: 25%; background-color: #F5F5F5; border-color: #C7CDD1;\"\u003e実施形態\u003c/td\u003e\n      \u003ctd style=\"border-color: #C7CDD1;\"\u003e完全オンライン\u003c/td\u003e\n    \u003c/tr\u003e\n    \u003ctr\u003e\n      \u003ctd style=\"background-color: #F5F5F5; border-color: #C7CDD1;\"\u003e開催日程\u003c/td\u003e\n      \u003ctd style=\"border-color: #C7CDD1;\"\u003e秋学期 金曜日３時限\u003c/td\u003e\n    \u003c/tr\u003e\n    \u003ctr\u003e\n      \u003ctd style=\"background-color: #F5F5F5; border-color: #C7CDD1;\"\u003e担当教員\u003c/td\u003e\n      \u003ctd style=\"border-color: #C7CDD1;\"\u003e野中 葉（ノナカ ヨウ）\u003c/td\u003e\n    \u003c/tr\u003e\n    \u003ctr\u003e\n      \u003ctd style=\"background-color: #F5F5F5; border-color: #C7CDD1;\"\u003e関連科目\u003c/td\u003e\n      \u003ctd style=\"border-color: #C7CDD1;\"\u003e\n          前提科目（関連）: 15451,15252,15251,15051\u003cbr\u003e\n      \u003c/td\u003e\n    \u003c/tr\u003e\n    \u003ctr\u003e\n      \u003ctd style=\"background-color: #F5F5F5; border-color: #C7CDD1;\"\u003e開講場所\u003c/td\u003e\n      \u003ctd style=\"border-color: #C7CDD1;\"\u003eSFC\u003c/td\u003e\n    \u003c/tr\u003e\n    \u003ctr\u003e\n      \u003ctd style=\"background-color: #F5F5F5; border-color: #C7CDD1;\"\u003e授業形態\u003c/td\u003e\n      \u003ctd style=\"border-color: #C7CDD1;\"\u003e講義\u003c/td\u003e\n    \u003c/tr\u003e\n    \u003ctr\u003e\n      \u003ctd style=\"background-color: #F5F5F5; border-color: #C7CDD1;\"\u003e履修者制限\u003c/td\u003e\n      \u003ctd style=\"border-color: #C7CDD1;\"\u003e\n          \u003cp\u003e履修人数を制限する\u003cbr\u003e\u003cbr\u003e受入学生数（予定）：約 50 人\u003cbr\u003e選抜方法：課題提出による選抜\u003cbr\u003e\u003cbr\u003e【課題内容】\u003cbr\u003e履修希望理由を８００字程度で記入しなさい。\u003cbr\u003e\u003cbr\u003e◯エントリー〆切日時：2020年9月28日（月） 17:00\u003cbr\u003e◯履修許可者発表日時：2020年9月30日（水） 17:00\u003cbr\u003e\u003cbr\u003e◯テキスト入力\u003cbr\u003e\u003c/p\u003e\n          \u003cp style=\"color: #856a5d;\"\u003eOnly the selected students can take this course.\u003cbr\u003e\u003cbr\u003eNumber of students in the class (scheduled) : About 50\u003cbr\u003ePre-registration screening by submitted an assignment\u003cbr\u003e\u003cbr\u003e【ASSIGNMENT】\u003cbr\u003e履修希望理由を８００字程度で記入しなさい。\u003cbr\u003e\u003cbr\u003e* Schedule: TBD\u003c/p\u003e\n      \u003c/td\u003e\n    \u003c/tr\u003e\n    \u003ctr\u003e\n      \u003ctd style=\"background-color: #F5F5F5; border-color: #C7CDD1;\"\u003e履修条件\u003c/td\u003e\n      \u003ctd style=\"border-color: #C7CDD1;\"\u003e\n        \u003cp\u003e\u003c/p\u003e\n        \u003cp style=\"color: #856a5d;\"\u003e\u003c/p\u003e\n        \u003cp\u003eなし\u003c/p\u003e\n        \u003cp style=\"color: #856a5d;\"\u003e\u003c/p\u003e\n      \u003c/td\u003e\n    \u003c/tr\u003e\n    \u003ctr\u003e\n      \u003ctd style=\"background-color: #F5F5F5; border-color: #C7CDD1;\"\u003e使用言語\u003c/td\u003e\n      \u003ctd style=\"border-color: #C7CDD1;\"\u003e日本語\u003c/td\u003e\n    \u003c/tr\u003e\n    \u003ctr\u003e\n      \u003ctd style=\"background-color: #F5F5F5; border-color: #C7CDD1;\"\u003e連絡先\u003c/td\u003e\n      \u003ctd style=\"border-color: #C7CDD1;\"\u003eyon@sfc.keio.ac.jp\u003c/td\u003e\n    \u003c/tr\u003e\n    \u003ctr\u003e\n      \u003ctd style=\"background-color: #F5F5F5; border-color: #C7CDD1;\"\u003e授業ホームページ\u003c/td\u003e\n      \u003ctd style=\"border-color: #C7CDD1;\"\u003enot available at the moment\u003c/td\u003e\n    \u003c/tr\u003e\n    \u003ctr\u003e\n      \u003ctd style=\"background-color: #F5F5F5; border-color: #C7CDD1;\"\u003e同一科目\u003c/td\u003e\n      \u003ctd style=\"border-color: #C7CDD1;\"\u003e\n        \u003cp\u003e\u003c/p\u003e\n        \u003cp style=\"color: #856a5d;\"\u003e\u003c/p\u003e\n      \u003c/td\u003e\n    \u003c/tr\u003e\n    \u003ctr\u003e\n      \u003ctd style=\"background-color: #F5F5F5; border-color: #C7CDD1;\"\u003e学生が利用する予定機材/ソフト等\u003c/td\u003e\n      \u003ctd style=\"border-color: #C7CDD1;\"\u003e\n        \u003cp\u003e\u003c/p\u003e\n        \u003cp style=\"color: #856a5d;\"\u003e\u003c/p\u003e\n      \u003c/td\u003e\n    \u003c/tr\u003e\n    \u003ctr\u003e\n      \u003ctd style=\"background-color: #F5F5F5; border-color: #C7CDD1;\"\u003e設置学部・研究科\u003c/td\u003e\n      \u003ctd style=\"border-color: #C7CDD1;\"\u003e総合政策・環境情報学部\u003c/td\u003e\n    \u003c/tr\u003e\n    \u003ctr\u003e\n      \u003ctd style=\"background-color: #F5F5F5; border-color: #C7CDD1;\"\u003e大学院プロジェクト名\u003c/td\u003e\n      \u003ctd style=\"border-color: #C7CDD1;\"\u003e\u003cp style=\"color: #856a5d;\"\u003e\u003c/p\u003e\u003c/td\u003e\n    \u003c/tr\u003e\n    \u003ctr\u003e\n      \u003ctd style=\"background-color: #F5F5F5; border-color: #C7CDD1;\"\u003e大学院プロジェクトサブメンバー\u003c/td\u003e\n      \u003ctd style=\"border-color: #C7CDD1;\"\u003e\n        \u003cp\u003e\u003c/p\u003e\n        \u003cp style=\"color: #856a5d;\"\u003e\u003c/p\u003e\n      \u003c/td\u003e\n    \u003c/tr\u003e\n    \u003ctr\u003e\n      \u003ctd style=\"background-color: #F5F5F5; border-color: #C7CDD1;\"\u003eゲストスピーカーの人数\u003c/td\u003e\n      \u003ctd style=\"border-color: #C7CDD1;\"\u003e0\u003c/td\u003e\n    \u003c/tr\u003e\n    \u003ctr\u003e\n      \u003ctd style=\"background-color: #F5F5F5; border-color: #C7CDD1;\"\u003e履修選抜・課題タイプ=テキスト登録可\u003c/td\u003e\n      \u003ctd style=\"border-color: #C7CDD1;\"\u003etrue\u003c/td\u003e\n    \u003c/tr\u003e\n    \u003ctr\u003e\n      \u003ctd style=\"background-color: #F5F5F5; border-color: #C7CDD1;\"\u003e履修選抜・選抜課題タイプ=ファイル登録可\u003c/td\u003e\n      \u003ctd style=\"border-color: #C7CDD1;\"\u003efalse\u003c/td\u003e\n    \u003c/tr\u003e\n    \u003ctr\u003e\n      \u003ctd style=\"background-color: #F5F5F5; border-color: #C7CDD1;\"\u003eGIGAサティフィケート対象\u003c/td\u003e\n      \u003ctd style=\"border-color: #C7CDD1;\"\u003e\u003c/td\u003e\n    \u003c/tr\u003e\n    \u003ctr\u003e\n      \u003ctd style=\"background-color: #F5F5F5; border-color: #C7CDD1;\"\u003e最終更新日\u003c/td\u003e\n      \u003ctd style=\"border-color: #C7CDD1;\"\u003e2020/07/22 10:43:06\u003c/td\u003e\n    \u003c/tr\u003e\n  \u003c/tbody\u003e\n\u003c/table\u003e\n\n\n\n\n\u003ch3 style=\"background-color: #394B58; color: white; padding-left: 8px; font-weight: bold;\"\u003e科目概要\u003c/h3\u003e\n\n\u003cp\u003e　本授業の目的は、様々な変化が生じている現代インドネシアの様々な事象を検証し、インドネシア社会を理解することにある。\u003cbr\u003e　現代のインドネシアは、1998年にスハルト権威主義体制が崩壊して以降、民主化と共に、経済成長も目覚ましい。また一方で、民主主義が定着し始めた社会において、イスラームが顕在化し、社会の様々な側面で力を発揮してきている。\u003cbr\u003e　授業では、個別の事例を検証しながら、このような特徴を持つインドネシアの実態や、社会の変化の様子を明らかにしていきたい。\u003cbr\u003e　授業で直接扱うのは、インドネシア社会であるが、類似の特徴を持つ、あるいは同様の変化を経験しているアジアの新興国や、混乱が続く中東イスラーム世界など、他の地域の事例も視野に入れつつ、話を進めていきたい。\u003c/p\u003e\n\u003cp style=\"color: #856a5d;\"\u003e\u003c/p\u003e\n\n\u003ch3 style=\"background-color: #394B58; color: white; padding-left: 8px; margin-bottom: 0; font-weight: bold;\"\u003e授業シラバス\u003c/h3\u003e\n\u003ch4 style=\"background-color: #ccecff; padding-left: 8px; margin-top: 0; font-weight: bold;\"\u003e主題と目標／授業の手法など\u003c/h4\u003e\n\u003cp\u003e　本授業の目的は、様々な変化を経験している現代インドネシアの様々な事象を検証し、インドネシア社会を理解することにある。\u003cbr\u003e　現代のインドネシアは、以下の点で非常に特徴的な国である。\u003cbr\u003e1）1998年に、それまで30年以上にわたり続いたスハルト権威主義体制が崩壊して以降、民主化に向けたプロセスが進行した。民主主義への移行がある程度成功した国として、国際的に知られる国になりつつある。\u003cbr\u003e2）民主化と並行して、近年では、経済発展が目覚ましく、人々の生活水準が向上して中間層が台頭した。巨大なマーケットを狙い、日本も含めた世界各国の企業が、進出し始めている。\u003cbr\u003e3）イスラームが人口の8割以上を占めるインドネシアでは、民主化と経済発展に伴い、宗教が衰退することなく、むしろ人々の紐帯としての役割を担い、社会の様々な側面で、顕在化してきている。イスラームに関連する商品やサービスが、「イスラーム・マーケット」と呼ばれ、活況を呈している。一方で、キリスト教徒や華人など、非イスラーム教徒との共存、宗教的不寛容の撲滅など、解決すべき課題は大きい。\u003cbr\u003e　授業では、個別の事例を検証しながら、このような特徴を持つインドネシアの実態や、社会の変化の様子を明らかにしていきたい。\u003cbr\u003e　授業で直接扱うのは、インドネシア社会であるが、類似の特徴を持つ、あるいは同様の変化を経験しているアジアの新興国や、混乱が続く中東イスラーム世界など、他の地域の事例も視野に入れつつ、話を進めていく。インドネシアはもとより、他のアジアの新興国や中東イスラーム世界に興味がある学生の参加も、大いに歓迎する。\u003cbr\u003e 授業は講義形式。前半（第5回まで）では、現代に至るまでのインドネシア社会（政治経済も含む）の変遷を、歴史的に論じる。後半（第6回以降）では、現代インドネシア社会に台頭するイスラームに関連して、様々な事例を取り上げ、現代国家と宗教の関係、現代社会におけるイスラームの役割を考えてみたい。\u003c/p\u003e\n\u003cp style=\"color: #856a5d;\"\u003e\u003c/p\u003e\n\n\u003ch4 style=\"background-color: #ccecff; padding-left: 8px; font-weight: bold;\"\u003e教材・参考文献\u003c/h4\u003e\n\u003cp\u003e（主な参考文献）\u003cbr\u003e倉沢愛子編『消費するインドネシア』慶應義塾大学出版 2013\u003cbr\u003e佐藤百合『経済大国インドネシア』中公新書 2011 \u003cbr\u003e野中葉『インドネシアのムスリムファッション』福村出版 2015、\u003cbr\u003e増原綾子『スハルト体制のインドネシア　個人支配の変容と1998年政変』東京大学出版会 2010 \u003cbr\u003e見市建『新興大国インドネシアの宗教市場と政治』NTT出版 2014\u003cbr\u003eその他の参考文献は、授業で適宜紹介。\u003c/p\u003e\n\n\u003ch4 style=\"background-color: #ccecff; padding-left: 8px; font-weight: bold;\"\u003e提出課題・試験・成績評価の方法など\u003c/h4\u003e\n\u003cp\u003e授業参加、毎回の授業後のコメントフォーム入力、期末レポートで評価します。\u003c/p\u003e\n\u003cp style=\"color: #856a5d;\"\u003e\u003c/p\u003e\n\n\u003ch4 style=\"background-color: #ccecff; padding-left: 8px; font-weight: bold;\"\u003e履修上の注意\u003c/h4\u003e\n\u003cp\u003e\u003c/p\u003e\n\u003cp style=\"color: #856a5d;\"\u003e\u003c/p\u003e\n\n\n\u003ch4 style=\"background-color: #ccecff; padding-left: 8px; font-weight: bold;\"\u003e授業計画\u003c/h4\u003e\n  \u003cp\u003e\n  \u003cu\u003e第1回 はじめに\u003c/u\u003e\n  \u003c/p\u003e\n  \u003cp\u003e\n  \u003c/p\u003e\u003cp\u003e授業の説明、イントロダクション\u003c/p\u003e\n  \u003cp style=\"color: #856a5d;\"\u003e\u003c/p\u003e\n  \n  \u003cp\u003e  \u003c/p\u003e\n  \u003chr\u003e\n  \u003cp\u003e\n  \u003cu\u003e第2回 インドネシアの建国\u003c/u\u003e\n  \u003c/p\u003e\n  \u003cp\u003e\n  \u003c/p\u003e\u003cp\u003e地理的・歴史的特性、建国理念パンチャシラ\u003cbr\u003e\u003c/p\u003e\n  \u003cp style=\"color: #856a5d;\"\u003e\u003c/p\u003e\n  \n  \u003cp\u003e  \u003c/p\u003e\n  \u003chr\u003e\n  \u003cp\u003e\n  \u003cu\u003e第3回 スハルト体制の光と影\u003c/u\u003e\n  \u003c/p\u003e\n  \u003cp\u003e\n  \u003c/p\u003e\u003cp\u003e開発優先政策による経済成長、生活の安定、教育水準の向上。一方で、反対勢力に対する徹底的な弾圧、富の集中\u003c/p\u003e\n  \u003cp style=\"color: #856a5d;\"\u003e\u003c/p\u003e\n  \n  \u003cp\u003e  \u003c/p\u003e\n  \u003chr\u003e\n  \u003cp\u003e\n  \u003cu\u003e第4回 レフォルマシ（改革）の実現\u003c/u\u003e\n  \u003c/p\u003e\n  \u003cp\u003e\n  \u003c/p\u003e\u003cp\u003eスハルト体制の終焉、民主化に向けた制度改革、選挙制度改革と選挙の実施\u003cbr\u003e\u003c/p\u003e\n  \u003cp style=\"color: #856a5d;\"\u003e\u003c/p\u003e\n  \n  \u003cp\u003e  \u003c/p\u003e\n  \u003chr\u003e\n  \u003cp\u003e\n  \u003cu\u003e第5回 経済成長の実現、中間層の出現\u003c/u\u003e\n  \u003c/p\u003e\n  \u003cp\u003e\n  \u003c/p\u003e\u003cp\u003e大国としての自信、ライフスタイルの変容、ソーシャルメディアの発展、疑似中間層の出現、いびつな発展\u003cbr\u003e\u003c/p\u003e\n  \u003cp style=\"color: #856a5d;\"\u003e\u003c/p\u003e\n  \n  \u003cp\u003e  \u003c/p\u003e\n  \u003chr\u003e\n  \u003cp\u003e\n  \u003cu\u003e第6回 イスラームの顕在化\u003c/u\u003e\n  \u003c/p\u003e\n  \u003cp\u003e\n  \u003c/p\u003e\u003cp\u003eインドネシアの宗教、公共宗教の理論\u003cbr\u003e\u003c/p\u003e\n  \u003cp style=\"color: #856a5d;\"\u003e\u003c/p\u003e\n  \n  \u003cp\u003e  \u003c/p\u003e\n  \u003chr\u003e\n  \u003cp\u003e\n  \u003cu\u003e第7回 ムスリマのヴェールと服装①\u003c/u\u003e\n  \u003c/p\u003e\n  \u003cp\u003e\n  \u003c/p\u003e\u003cp\u003eジルバブ着用運動、ファッションとしてのヴェール\u003cbr\u003e\u003c/p\u003e\n  \u003cp style=\"color: #856a5d;\"\u003e\u003c/p\u003e\n  \n  \u003cp\u003e  \u003c/p\u003e\n  \u003chr\u003e\n  \u003cp\u003e\n  \u003cu\u003e第8回 ムスリマのヴェールと服装②\u003c/u\u003e\n  \u003c/p\u003e\n  \u003cp\u003e\n  \u003c/p\u003e\u003cp\u003eジルバブ着用運動、ファッションとしてのヴェール\u003cbr\u003e\u003c/p\u003e\n  \u003cp style=\"color: #856a5d;\"\u003e\u003c/p\u003e\n  \n  \u003cp\u003e  \u003c/p\u003e\n  \u003chr\u003e\n  \u003cp\u003e\n  \u003cu\u003e第9回 大学ダアワ運動のひろがり\u003c/u\u003e\n  \u003c/p\u003e\n  \u003cp\u003e\n  \u003c/p\u003e\u003cp\u003e世俗大学のエリート学生たちのイスラームへの傾倒、社会への影響\u003cbr\u003e\u003c/p\u003e\n  \u003cp style=\"color: #856a5d;\"\u003e\u003c/p\u003e\n  \n  \u003cp\u003e  \u003c/p\u003e\n  \u003chr\u003e\n  \u003cp\u003e\n  \u003cu\u003e第10回 政治的イスラームの台頭と停滞\u003c/u\u003e\n  \u003c/p\u003e\n  \u003cp\u003e\n  \u003c/p\u003e\u003cp\u003eイスラーム政党の成長と停滞、イスラーム主義、「アラブの春」との関連\u003c/p\u003e\n  \u003cp style=\"color: #856a5d;\"\u003e\u003c/p\u003e\n  \n  \u003cp\u003e  \u003c/p\u003e\n  \u003chr\u003e\n  \u003cp\u003e\n  \u003cu\u003e第11回 宗教対立、不寛容\u003c/u\u003e\n  \u003c/p\u003e\n  \u003cp\u003e\n  \u003c/p\u003e\u003cp\u003e宗教的不寛容の拡大、イスラーム的解決の模索\u003cbr\u003e\u003c/p\u003e\n  \u003cp style=\"color: #856a5d;\"\u003e\u003c/p\u003e\n  \n  \u003cp\u003e  \u003c/p\u003e\n  \u003chr\u003e\n  \u003cp\u003e\n  \u003cu\u003e第12回 イスラーム的文学、イスラーム的映画\u003c/u\u003e\n  \u003c/p\u003e\n  \u003cp\u003e\n  \u003c/p\u003e\u003cp\u003e「イスラーム的なことは良いこと」という価値観の醸成、共有\u003c/p\u003e\n  \u003cp style=\"color: #856a5d;\"\u003e\u003c/p\u003e\n  \n  \u003cp\u003e  \u003c/p\u003e\n  \u003chr\u003e\n  \u003cp\u003e\n  \u003cu\u003e第13回 イスラーム・マーケット①\u003c/u\u003e\n  \u003c/p\u003e\n  \u003cp\u003e\n  \u003c/p\u003e\u003cp\u003eハラール・ビジネス、ムスリム観光、日本とインドネシアの新しい関係\u003c/p\u003e\n  \u003cp style=\"color: #856a5d;\"\u003e\u003c/p\u003e\n  \n  \u003cp\u003e  \u003c/p\u003e\n  \u003chr\u003e\n  \u003cp\u003e\n  \u003cu\u003e第14回 イスラーム・マーケット②\u003c/u\u003e\n  \u003c/p\u003e\n  \u003cp\u003e\n  \u003c/p\u003e\u003cp\u003eハラール・ビジネス、ムスリム観光、日本とインドネシアの新しい関係\u003c/p\u003e\n  \u003cp style=\"color: #856a5d;\"\u003e\u003c/p\u003e\n  \n  \u003cp\u003e  \u003c/p\u003e\n  \u003chr\u003e\n  \u003cp\u003e\n  \u003cu\u003e第15回 まとめと今後の展望\u003c/u\u003e\n  \u003c/p\u003e\n  \u003cp\u003e\n  \u003c/p\u003e\u003cp\u003e\u003c/p\u003e\n  \u003cp style=\"color: #856a5d;\"\u003e\u003c/p\u003e\n  \n  \u003cp\u003e  \u003c/p\u003e\n  \u003chr\u003e\n\n  \u003cu\u003e15回目に相当するその他の授業計画\u003c/u\u003e\u003cbr\u003e\n  \u003cp\u003eまとめと今後の展望\u003cbr\u003e\u003c/p\u003e\n  \u003cp style=\"color: #856a5d;\"\u003e\u003c/p\u003e\n","course_code":"インドネシア文化論","default_view":"modules","root_account_id":1,"enrollment_term_id":3,"license":null,"grade_passback_setting":null,"end_at":null,"public_syllabus":false,"public_syllabus_to_auth":true,"storage_quota_mb":30000,"is_public_to_auth_users":true,"term":{"id":3,"name":"2020年秋学期","start_at":null,"end_at":null,"created_at":"2020-09-03T21:25:41Z","workflow_state":"active","grading_period_group_id":null},"apply_assignment_group_weights":false,"calendar":{"ics":"https://sol.sfc.keio.ac.jp/feeds/calendars/course_JSqH1QBTdOC4q462wEEufQIn4ZIgfLJIqQNx80MI.ics"},"time_zone":"Asia/Tokyo","blueprint":false,"enrollments":[],"hide_final_grades":false,"workflow_state":"available","restrict_enrollments_to_course_dates":false,"overridden_course_visibility":""}